cli/config_manager.py
cli/mova.py
cli/mova_voice.py
cli/rss_server.py
cli/security_manager.py
cli/service_connectors.py
server/app.py
server/mqtt_adapter.py
mova-0.1.4.dist-info/METADATA
mova-0.1.4.dist-info/WHEEL
mova-0.1.4.dist-info/entry_points.txt
mova-0.1.4.dist-info/top_level.txt
mova-0.1.4.dist-info/RECORD
