Metadata-Version: 2.4
Name: mova
Version: 0.1.4
Summary: Lekka warstwa komunikacji między frontendem, backendem, IoT i LLM
Author-email: Tom Sapletta <info@softreck.dev>
Classifier: Development Status :: 3 - Alpha
Classifier: Intended Audience :: Developers
Classifier: License :: OSI Approved :: Apache Software License
Classifier: Programming Language :: Python :: 3
Classifier: Programming Language :: Python :: 3.11
Classifier: Programming Language :: Python :: 3.12
Requires-Python: >=3.11
